{
  "Dart": 337363468,
  "BoardGame": 340853763,
  "FastHatch": 3224399851,
  "PetMatch": 40934445,
  "TeamEnchant": 71327311,
  "BasicComp": 201279,
  "AutoFish": 83854415,
  "QuestBoard": 13622977,
  "FastBox": 16318340,
  "Auto Obby": 3095048,
  "AutoMaze": 161325,
  "FastComp": 88294,
  "Trick Or Treat": 9213139,
  "GemGenie": 24444146,
  "Christmas Candy": 46367135,
  "Jolly Trio": 1596628,
  "Ultra Infinity Farm": 1624367,
  "Auto Dance": 27323769,
  "Petal Farm": 740108,
  "BubbleComp": 39892485
}