{
  "Dart": 346632870,
  "BoardGame": 354330886,
  "FastHatch": 3340268673,
  "PetMatch": 43224844,
  "TeamEnchant": 72283060,
  "BasicComp": 201809,
  "AutoFish": 85016333,
  "QuestBoard": 15252937,
  "FastBox": 17230935,
  "Auto Obby": 3101399,
  "AutoMaze": 161365,
  "FastComp": 88294,
  "Trick Or Treat": 9213139,
  "GemGenie": 25140388,
  "Christmas Candy": 46367195,
  "Jolly Trio": 1596628,
  "Ultra Infinity Farm": 1624367,
  "Auto Dance": 27328429,
  "Petal Farm": 760688,
  "BubbleComp": 39917737,
  "AG AutoFarm": 3727676
}