{
  "Dart": 332918225,
  "BoardGame": 334666930,
  "FastHatch": 3175921774,
  "PetMatch": 39982333,
  "TeamEnchant": 70870848,
  "BasicComp": 201129,
  "AutoFish": 83331691,
  "QuestBoard": 12585068,
  "FastBox": 15867957,
  "Auto Obby": 3093298,
  "AutoMaze": 161285,
  "FastComp": 88294,
  "Trick Or Treat": 9213139,
  "GemGenie": 22709668,
  "Christmas Candy": 46367105,
  "Jolly Trio": 1596628,
  "Ultra Infinity Farm": 1624367,
  "Auto Dance": 27323769,
  "Petal Farm": 739357,
  "BubbleComp": 39890715
}