{
  "Dart": 339593139,
  "BoardGame": 344715678,
  "FastHatch": 3250567379,
  "PetMatch": 41261459,
  "TeamEnchant": 71579924,
  "BasicComp": 201279,
  "AutoFish": 83957478,
  "QuestBoard": 14041759,
  "FastBox": 16685574,
  "Auto Obby": 3096588,
  "AutoMaze": 161325,
  "FastComp": 88294,
  "Trick Or Treat": 9213139,
  "GemGenie": 24953830,
  "Christmas Candy": 46367135,
  "Jolly Trio": 1596628,
  "Ultra Infinity Farm": 1624367,
  "Auto Dance": 27328369,
  "Petal Farm": 750518,
  "BubbleComp": 39892485
}