{
  "Dart": 349956137,
  "BoardGame": 359155997,
  "FastHatch": 3378918858,
  "PetMatch": 44416048,
  "TeamEnchant": 72548540,
  "BasicComp": 201809,
  "AutoFish": 85736895,
  "QuestBoard": 15664840,
  "FastBox": 17377545,
  "Auto Obby": 3102419,
  "AutoMaze": 161855,
  "FastComp": 88294,
  "Trick Or Treat": 9213139,
  "GemGenie": 25439394,
  "Christmas Candy": 46367265,
  "Jolly Trio": 1596628,
  "Ultra Infinity Farm": 1624367,
  "Auto Dance": 27328429,
  "Petal Farm": 761458,
  "BubbleComp": 39950508,
  "AG AutoFarm": 3727676
}