{
  "Dart": 327962192,
  "BoardGame": 327755575,
  "FastHatch": 3101552916,
  "PetMatch": 38671743,
  "TeamEnchant": 70024545,
  "BasicComp": 200709,
  "AutoFish": 82448390,
  "QuestBoard": 10501460,
  "FastBox": 15379243,
  "Auto Obby": 3091848,
  "AutoMaze": 161285,
  "FastComp": 88294,
  "Trick Or Treat": 9213139,
  "GemGenie": 18925854,
  "Christmas Candy": 46367075,
  "Jolly Trio": 1596628,
  "Ultra Infinity Farm": 1624367,
  "Auto Dance": 27323769,
  "Petal Farm": 735037,
  "BubbleComp": 39867983
}