{
  "Dart": 339286851,
  "BoardGame": 343801118,
  "FastHatch": 3239844605,
  "PetMatch": 41202524,
  "TeamEnchant": 71515723,
  "BasicComp": 201279,
  "AutoFish": 83906848,
  "QuestBoard": 14011398,
  "FastBox": 16614522,
  "Auto Obby": 3096448,
  "AutoMaze": 161325,
  "FastComp": 88294,
  "Trick Or Treat": 9213139,
  "GemGenie": 24880751,
  "Christmas Candy": 46367135,
  "Jolly Trio": 1596628,
  "Ultra Infinity Farm": 1624367,
  "Auto Dance": 27328369,
  "Petal Farm": 750458,
  "BubbleComp": 39892485
}