{
  "Dart": 351140164,
  "BoardGame": 361239766,
  "FastHatch": 3388189940,
  "PetMatch": 44605495,
  "TeamEnchant": 72593037,
  "BasicComp": 201839,
  "AutoFish": 85881818,
  "QuestBoard": 15668550,
  "FastBox": 17395495,
  "Auto Obby": 3103430,
  "AutoMaze": 161855,
  "FastComp": 88294,
  "Trick Or Treat": 9213139,
  "GemGenie": 25551642,
  "Christmas Candy": 46367265,
  "Jolly Trio": 1596628,
  "Ultra Infinity Farm": 1624367,
  "Auto Dance": 27328429,
  "Petal Farm": 761488,
  "BubbleComp": 39951418,
  "AG AutoFarm": 3727676
}