{
  "Dart": 345821931,
  "BoardGame": 353369267,
  "FastHatch": 3331078023,
  "PetMatch": 42747064,
  "TeamEnchant": 72214279,
  "BasicComp": 201809,
  "AutoFish": 84877711,
  "QuestBoard": 14973326,
  "FastBox": 17135361,
  "Auto Obby": 3101269,
  "AutoMaze": 161365,
  "FastComp": 88294,
  "Trick Or Treat": 9213139,
  "GemGenie": 25095798,
  "Christmas Candy": 46367195,
  "Jolly Trio": 1596628,
  "Ultra Infinity Farm": 1624367,
  "Auto Dance": 27328429,
  "Petal Farm": 760468,
  "BubbleComp": 39917487,
  "AG AutoFarm": 3727226
}