{
  "Dart": 336766506,
  "BoardGame": 339965941,
  "FastHatch": 3219170635,
  "PetMatch": 40915735,
  "TeamEnchant": 71303471,
  "BasicComp": 201279,
  "AutoFish": 83793702,
  "QuestBoard": 13326327,
  "FastBox": 16207696,
  "Auto Obby": 3094708,
  "AutoMaze": 161325,
  "FastComp": 88294,
  "Trick Or Treat": 9213139,
  "GemGenie": 24231479,
  "Christmas Candy": 46367135,
  "Jolly Trio": 1596628,
  "Ultra Infinity Farm": 1624367,
  "Auto Dance": 27323769,
  "Petal Farm": 739588,
  "BubbleComp": 39892035
}