{
  "Dart": 339499442,
  "BoardGame": 344336500,
  "FastHatch": 3246603741,
  "PetMatch": 41244106,
  "TeamEnchant": 71556634,
  "BasicComp": 201279,
  "AutoFish": 83939718,
  "QuestBoard": 14022919,
  "FastBox": 16638293,
  "Auto Obby": 3096588,
  "AutoMaze": 161325,
  "FastComp": 88294,
  "Trick Or Treat": 9213139,
  "GemGenie": 24891331,
  "Christmas Candy": 46367135,
  "Jolly Trio": 1596628,
  "Ultra Infinity Farm": 1624367,
  "Auto Dance": 27328369,
  "Petal Farm": 750518,
  "BubbleComp": 39892485
}