{
  "Dart": 335096584,
  "BoardGame": 337363420,
  "FastHatch": 3191988122,
  "PetMatch": 40511477,
  "TeamEnchant": 70967319,
  "BasicComp": 201129,
  "AutoFish": 83570639,
  "QuestBoard": 12943020,
  "FastBox": 15933147,
  "Auto Obby": 3093478,
  "AutoMaze": 161285,
  "FastComp": 88294,
  "Trick Or Treat": 9213139,
  "GemGenie": 23649090,
  "Christmas Candy": 46367135,
  "Jolly Trio": 1596628,
  "Ultra Infinity Farm": 1624367,
  "Auto Dance": 27323769,
  "Petal Farm": 739417,
  "BubbleComp": 39890715
}