{
  "Dart": 348539248,
  "BoardGame": 356224005,
  "FastHatch": 3360772923,
  "PetMatch": 43959221,
  "TeamEnchant": 72463297,
  "BasicComp": 201809,
  "AutoFish": 85297063,
  "QuestBoard": 15516997,
  "FastBox": 17316306,
  "Auto Obby": 3102119,
  "AutoMaze": 161365,
  "FastComp": 88294,
  "Trick Or Treat": 9213139,
  "GemGenie": 25347913,
  "Christmas Candy": 46367265,
  "Jolly Trio": 1596628,
  "Ultra Infinity Farm": 1624367,
  "Auto Dance": 27328429,
  "Petal Farm": 761408,
  "BubbleComp": 39941558,
  "AG AutoFarm": 3727676
}