{
  "Dart": 332545471,
  "BoardGame": 334251516,
  "FastHatch": 3173067807,
  "PetMatch": 39891231,
  "TeamEnchant": 70802636,
  "BasicComp": 201129,
  "AutoFish": 83216663,
  "QuestBoard": 12512817,
  "FastBox": 15836347,
  "Auto Obby": 3093298,
  "AutoMaze": 161285,
  "FastComp": 88294,
  "Trick Or Treat": 9213139,
  "GemGenie": 22469568,
  "Christmas Candy": 46367105,
  "Jolly Trio": 1596628,
  "Ultra Infinity Farm": 1624367,
  "Auto Dance": 27323769,
  "Petal Farm": 739357,
  "BubbleComp": 39890715
}